amap_mcp_server/__init__.py
amap_mcp_server/__main__.py
amap_mcp_server/server.py
mseep_amap_mcp_server-0.1.10.dist-info/licenses/LICENSE
mseep_amap_mcp_server-0.1.10.dist-info/METADATA
mseep_amap_mcp_server-0.1.10.dist-info/WHEEL
mseep_amap_mcp_server-0.1.10.dist-info/entry_points.txt
mseep_amap_mcp_server-0.1.10.dist-info/top_level.txt
mseep_amap_mcp_server-0.1.10.dist-info/RECORD
